flask_ngrok3.py
flask_ngrok3-0.3.1.dist-info/LICENSE
flask_ngrok3-0.3.1.dist-info/METADATA
flask_ngrok3-0.3.1.dist-info/WHEEL
flask_ngrok3-0.3.1.dist-info/top_level.txt
flask_ngrok3-0.3.1.dist-info/RECORD
