Metadata-Version: 2.1
Name: flask-ngrok3
Version: 0.3.1
Summary: A successor to flask-ngrok and flask-ngrok2 for demo Flask apps using ngrok.
Home-page: https://github.com/Partycode/flask-ngrok3
Author: Partycode
Keywords: flask ngrok demo
Classifier: Programming Language :: Python :: 3.6
Classifier: License :: OSI Approved :: Apache Software License
Classifier: Operating System :: OS Independent
License-File: LICENSE
Requires-Dist: Flask (>=0.8)
Requires-Dist: requests
